bizkit/__init__.py
bizkit/anomaly.py
bizkit/customer_clustering.py
bizkit/hyperhelper.py
bizkit/market-basket-analysis.py
bizkit/time_to_event.py
bizkit-0.0.4.dist-info/LICENSE
bizkit-0.0.4.dist-info/METADATA
bizkit-0.0.4.dist-info/WHEEL
bizkit-0.0.4.dist-info/top_level.txt
bizkit-0.0.4.dist-info/RECORD
