Metadata-Version: 2.1
Name: bizkit
Version: 0.0.4
Summary: A package that streamlines business data analytics
Home-page: https://github.com/pypa/bizkit
Author: Bassim Eledath, Lynn He, Christine Zhu, Amanda Ma
Author-email: bassimfaizal@gmail.com
License: UNKNOWN
Platform: UNKNOWN
Classifier: Programming Language :: Python :: 3
Classifier: License :: OSI Approved :: MIT License
Classifier: Operating System :: OS Independent
Requires-Dist: pandas
Requires-Dist: numpy
Requires-Dist: lifelines
Requires-Dist: bokeh
Requires-Dist: sklearn
Requires-Dist: mlxtend
Requires-Dist: d3fdgraph
